ShenghuaGuancaiQuantuiWenji2020112Fix1/README.md
ShenghuaGuancaiQuantuiWenji2020112Fix1/__init__.py
ShenghuaGuancaiQuantuiWenji2020112Fix1/__main__.py
ShenghuaGuancaiQuantuiWenji2020112Fix1/file.epub
ShenghuaGuancaiQuantuiWenji2020112Fix1/index.html
ShenghuaGuancaiQuantuiWenji2020112Fix1/css/__init__.py
ShenghuaGuancaiQuantuiWenji2020112Fix1/css/annotations.css
ShenghuaGuancaiQuantuiWenji2020112Fix1/css/main.css
ShenghuaGuancaiQuantuiWenji2020112Fix1/css/normalize.css
ShenghuaGuancaiQuantuiWenji2020112Fix1/css/popup.css
ShenghuaGuancaiQuantuiWenji2020112Fix1/font/__init__.py
ShenghuaGuancaiQuantuiWenji2020112Fix1/font/fontello.eot
ShenghuaGuancaiQuantuiWenji2020112Fix1/font/fontello.svg
ShenghuaGuancaiQuantuiWenji2020112Fix1/font/fontello.ttf
ShenghuaGuancaiQuantuiWenji2020112Fix1/font/fontello.woff
ShenghuaGuancaiQuantuiWenji2020112Fix1/img/__init__.py
ShenghuaGuancaiQuantuiWenji2020112Fix1/img/annotator-glyph-sprite.png
ShenghuaGuancaiQuantuiWenji2020112Fix1/img/annotator-icon-sprite.png
ShenghuaGuancaiQuantuiWenji2020112Fix1/img/apple-touch-icon.png
ShenghuaGuancaiQuantuiWenji2020112Fix1/img/cancelfullscreen.png
ShenghuaGuancaiQuantuiWenji2020112Fix1/img/close.png
ShenghuaGuancaiQuantuiWenji2020112Fix1/img/fullscreen.png
ShenghuaGuancaiQuantuiWenji2020112Fix1/img/loader.gif
ShenghuaGuancaiQuantuiWenji2020112Fix1/img/menu-icon.png
ShenghuaGuancaiQuantuiWenji2020112Fix1/img/save.png
ShenghuaGuancaiQuantuiWenji2020112Fix1/img/saved.png
ShenghuaGuancaiQuantuiWenji2020112Fix1/img/settings-s.png
ShenghuaGuancaiQuantuiWenji2020112Fix1/img/settings.png
ShenghuaGuancaiQuantuiWenji2020112Fix1/img/star.png
ShenghuaGuancaiQuantuiWenji2020112Fix1/js/__init__.py
ShenghuaGuancaiQuantuiWenji2020112Fix1/js/epub.js
ShenghuaGuancaiQuantuiWenji2020112Fix1/js/epub.min.js
ShenghuaGuancaiQuantuiWenji2020112Fix1/js/epub.min.map
ShenghuaGuancaiQuantuiWenji2020112Fix1/js/hooks.min.js
ShenghuaGuancaiQuantuiWenji2020112Fix1/js/hooks.min.map
shenghua_guancai_quantui_wenji_2020_11_2_fix1-2025.3.24.0.dist-info/METADATA
shenghua_guancai_quantui_wenji_2020_11_2_fix1-2025.3.24.0.dist-info/WHEEL
shenghua_guancai_quantui_wenji_2020_11_2_fix1-2025.3.24.0.dist-info/entry_points.txt
shenghua_guancai_quantui_wenji_2020_11_2_fix1-2025.3.24.0.dist-info/top_level.txt
shenghua_guancai_quantui_wenji_2020_11_2_fix1-2025.3.24.0.dist-info/RECORD
